libratom/__init__.py
libratom/cli/__init__.py
libratom/cli/cli.py
libratom/cli/subcommands.py
libratom/cli/utils.py
libratom/data/__init__.py
libratom/data/eml_dump_input.schema.json
libratom/data/media_types.json
libratom/data/perm-headers.csv
libratom/lib/__init__.py
libratom/lib/base.py
libratom/lib/concurrency.py
libratom/lib/constants.py
libratom/lib/core.py
libratom/lib/database.py
libratom/lib/download.py
libratom/lib/eml.py
libratom/lib/entities.py
libratom/lib/exceptions.py
libratom/lib/headers.py
libratom/lib/mbox.py
libratom/lib/pff.py
libratom/lib/report.py
libratom/lib/utils.py
libratom/models/__init__.py
libratom/models/attachment.py
libratom/models/configuration.py
libratom/models/entity.py
libratom/models/file_report.py
libratom/models/header_field.py
libratom/models/message.py
libratom/scripts/download_edrm_zipped_files.py
libratom/scripts/download_sample_mbox_files.py
libratom/scripts/get_media_type_list.py
libratom-0.7.1.data/data/libratom/data/__init__.py
libratom-0.7.1.data/data/libratom/data/eml_dump_input.schema.json
libratom-0.7.1.data/data/libratom/data/media_types.json
libratom-0.7.1.data/data/libratom/data/perm-headers.csv
libratom-0.7.1.dist-info/LICENSE
libratom-0.7.1.dist-info/METADATA
libratom-0.7.1.dist-info/WHEEL
libratom-0.7.1.dist-info/entry_points.txt
libratom-0.7.1.dist-info/pbr.json
libratom-0.7.1.dist-info/top_level.txt
libratom-0.7.1.dist-info/RECORD
