Metadata-Version: 2.1
Name: libratom
Version: 0.7.1
Summary: Python library and supporting utilities to parse and process PST and mbox email sources
Home-page: https://github.com/libratom/libratom
Author: RATOM
Author-email: ratom@protonmail.com
License: MIT
Platform: UNKNOWN
Classifier: Development Status :: 5 - Production/Stable
Classifier: Environment :: Console
Requires-Python: >=3.8
License-File: LICENSE
